[
    {
        "id": 285,
        "Count": 1,
        "tag": {
            "ench": [],
            "Unbreakable": 1,
            "HideFlags": 254,
            "display": {
                "Lore": [
                    "§8Breaking Power 1",
                    "",
                    "§7Defense: §a+13 §9(Refined +13)",
                    "§7Mining Speed: §a+510",
                    "",
                    "§9Compact VI §822,171",
                    "§7Gain §a6% §7extra Mining exp",
                    "§7with §a0.4% §7chance to drop an",
                    "§7enchanted item.",
                    "§850k blocks to tier up!",
                    "§9Efficiency VI",
                    "§7Grants §a+130 §6⸕ Mining",
                    "§6Speed§7.",
                    "§9Experience III",
                    "§7Grants a §a37.5% §7chance for",
                    "§7mobs and ores to drop double",
                    "§7experience.",
                    "§9Fortune III",
                    "§7Grants §a+30 §6☘ Mining",
                    "§6Fortune§7, which increases your",
                    "§7chance for multiple drops.",
                    "§9Telekinesis I",
                    "§7Block and mob drops go directly",
                    "§7into your inventory.",
                    "",
                    "§7When mining End Stone with this",
                    "§7pickaxe, Endermites won't spawn,", 
                    "§7experience will be dropped!", 
                    "§7§a5%§7 chance to drop an extra", 
                    "§7End Stone block.", 
                    "", 
                    "§9Refined Bonus", 
                    "§7Gain §a+4% §7Mining exp.", 
                    "§7Gain a §a0.1% §7chance to drop", 
                    "§7an enchanted block for ores that", 
                    "§7you mine.", 
                    "", 
                    "§5§lEPIC PICKAXE"], 
                "Name": "§5Refined Stonk"},
            "ExtraAttributes": {
                "modifier": "refined", 
                "compact_blocks": 22171, 
                "originTag": "SHOP_PURCHASE", 
                "id": "STONK_PICKAXE", 
                "enchantments": {
                    "efficiency": 6, 
                    "fortune": 3, 
                    "compact": 6, 
                    "telekinesis": 1, 
                    "experience": 3}, 
                "uuid": "a4268f56-470f-4223-80a2-36ad67d43820", 
                "anvil_uses": 1, 
                "timestamp": "9/27/19 9: 28 PM"}
            }, 
        "Damage": 0},
        {}, {}, {}, {}, {}, {}, {}, {"id": 399, "Count": 1, "tag": {"HideFlags": 254, "display": {"Lore": ["§7View all of your SkyBlock", "§7progress, including your Skills,", "§7Collections, Recipes, and more!", "", "§eClick to open!"], "Name": "§aSkyBlock Menu §7(Right Click)"}, "ExtraAttributes": {"id": "SKYBLOCK_MENU"}}, "Damage": 0}, {}, {}, {}, {}, {}, {}, {}, {}, {}, {}, {}, {}, {}, {}, {}, {}, {}, {"id": 340, "Count": 1, "tag": {"HideFlags": 254, "display": {"Lore": ["§7Combine this Book in an Anvil", "§7with a weapon to gain §c+5❁", "§cStrength§7!", "", "§7§8In the midst of chaos, there", "§8is also opportunity.", "§8 - Sun Tzu", "", "§6§lLEGENDARY"], "Name": "§6The Art of War"}, "ExtraAttributes": {"originTag": "SHOP_PURCHASE", "id": "THE_ART_OF_WAR", "uuid": "6d29e418-f87e-4532-8a5b-33b4d3f94085", "timestamp": "4/19/21 4: 40 PM"}}, "Damage": 0}, {}, {}, {}, {}, {}, {}, {}, {}, {"id": 158, "Count": 1, "tag": {"ench": [], "HideFlags": 254, "display": {"Lore": ["§7§8Enriched with Magic Find", "", "§7Strength: §c+12 §9(Strong +12)", "§7Crit Damage: §c+12% §9(Strong +12%)", "", "§7Defense: §a+4 §9(Strong +4)", "§7Magic Find: §a+0.5", "", "§7Automatically turns certain", "§7materials in your inventory into", "§7their enchanted form.", "", "§eRight-click to configure!", "", "§d§l§ka§r §d§l§d§lMYTHIC ACCESSORY §d§l§ka"], "Name": "§dStrong Personal Compactor 7000"}, "ExtraAttributes": {"rarity_upgrades": 1, "modifier": "strong", "originTag": "PERSONAL_COMPACTOR_7000", "uuid": "ebbf4f7a-3fc8-47f6-ba46-97f3438b5d1d", "personal_compact_0": "ENCHANTED_DARK_OAK_LOG", "talisman_enrichment": "MAGIC_FIND", "personal_compact_2": "ENCHANTED_LAPIS_LAZULI", "personal_compact_1": "ENCHANTED_COBBLESTONE", "personal_compact_7": "ENCHANTED_DIAMOND", "id": "PERSONAL_COMPACTOR_7000", "personal_compact_4": "ENCHANTED_BONE", "personal_compact_3": "ENCHANTED_STRING", "personal_compact_6": "ENCHANTED_DIAMOND_BLOCK", "timestamp": "6/12/20 1: 00 PM", "personal_compact_5": "ENCHANTED_ROTTEN_FLESH"}}, "Damage": 0}]